heytextual/__init__.py
heytextual/client.py
heytextual/endpoints.py
tests/__init__.py
tests/test_client.py
heytextual-0.1.7.dist-info/LICENSE
heytextual-0.1.7.dist-info/METADATA
heytextual-0.1.7.dist-info/WHEEL
heytextual-0.1.7.dist-info/entry_points.txt
heytextual-0.1.7.dist-info/top_level.txt
heytextual-0.1.7.dist-info/RECORD
