Metadata-Version: 2.1
Name: heytextual
Version: 0.1.7
Summary: A Python SDK for the HeyTextual API
Home-page: https://github.com/danielfergu/heytextual-python
Author: Daniel Fernandez Gutierrez
Author-email: dfernandez@heytextual.com
License: MIT
Keywords: API SDK HEYTEXTUAL
License-File: LICENSE
Requires-Dist: requests
